tensorflow_similarity/__init__.py
tensorflow_similarity/algebra.py
tensorflow_similarity/base_indexer.py
tensorflow_similarity/callbacks.py
tensorflow_similarity/indexer.py
tensorflow_similarity/layers.py
tensorflow_similarity/schedules.py
tensorflow_similarity/types.py
tensorflow_similarity/utils.py
tensorflow_similarity/api/__init__.py
tensorflow_similarity/architectures/__init__.py
tensorflow_similarity/architectures/efficientnet.py
tensorflow_similarity/architectures/resnet18.py
tensorflow_similarity/architectures/resnet50.py
tensorflow_similarity/architectures/utils.py
tensorflow_similarity/augmenters/__init__.py
tensorflow_similarity/augmenters/augmenter.py
tensorflow_similarity/augmenters/barlow.py
tensorflow_similarity/augmenters/contrastive.py
tensorflow_similarity/augmenters/simclr.py
tensorflow_similarity/augmenters/augmentation_utils/__init__.py
tensorflow_similarity/augmenters/augmentation_utils/blur.py
tensorflow_similarity/augmenters/augmentation_utils/color_jitter.py
tensorflow_similarity/augmenters/augmentation_utils/cropping.py
tensorflow_similarity/augmenters/augmentation_utils/flip.py
tensorflow_similarity/augmenters/augmentation_utils/random_apply.py
tensorflow_similarity/augmenters/augmentation_utils/solarize.py
tensorflow_similarity/classification_metrics/__init__.py
tensorflow_similarity/classification_metrics/binary_accuracy.py
tensorflow_similarity/classification_metrics/classification_metric.py
tensorflow_similarity/classification_metrics/f1_score.py
tensorflow_similarity/classification_metrics/false_positive_rate.py
tensorflow_similarity/classification_metrics/negative_predictive_value.py
tensorflow_similarity/classification_metrics/precision.py
tensorflow_similarity/classification_metrics/recall.py
tensorflow_similarity/classification_metrics/utils.py
tensorflow_similarity/distances/__init__.py
tensorflow_similarity/distances/cosine.py
tensorflow_similarity/distances/distance.py
tensorflow_similarity/distances/euclidean.py
tfsim_nightly-0.18.0.dev13.dist-info/LICENSE
tfsim_nightly-0.18.0.dev13.dist-info/METADATA
tfsim_nightly-0.18.0.dev13.dist-info/WHEEL
tfsim_nightly-0.18.0.dev13.dist-info/top_level.txt
tfsim_nightly-0.18.0.dev13.dist-info/RECORD
