Metadata-Version: 2.1
Name: tfsim-nightly
Version: 0.18.0.dev13
Summary: Metric Learning for Humans
Home-page: https://github.com/tensorflow/similarity
Author: Tensorflow Similarity authors
Author-email: tf-similarity@google.com
License: Apache License 2.0
Platform: UNKNOWN
Classifier: Development Status :: 5 - Production/Stable
Classifier: Environment :: Console
Classifier: License :: OSI Approved :: Apache Software License
Classifier: Intended Audience :: Science/Research
Classifier: Programming Language :: Python :: 3
Classifier: Topic :: Scientific/Engineering :: Artificial Intelligence
License-File: LICENSE
Requires-Dist: numpy
Requires-Dist: pandas
Requires-Dist: tabulate
Requires-Dist: tensorflow-datasets >=4.2
Requires-Dist: tqdm
Provides-Extra: benchmark
Requires-Dist: keras-tuner ; extra == 'benchmark'
Provides-Extra: dev
Requires-Dist: flake8 ; extra == 'dev'
Requires-Dist: black ; extra == 'dev'
Requires-Dist: isort ; extra == 'dev'
Requires-Dist: coverage ; extra == 'dev'
Requires-Dist: pytest ; extra == 'dev'
Requires-Dist: pre-commit ; extra == 'dev'
Requires-Dist: mkdocs ; extra == 'dev'
Requires-Dist: mkdocs-autorefs ; extra == 'dev'
Requires-Dist: mkdocs-material ; extra == 'dev'
Requires-Dist: mkdocstrings ; extra == 'dev'
Requires-Dist: mypy <=0.982 ; extra == 'dev'
Requires-Dist: pytype ; extra == 'dev'
Requires-Dist: setuptools ; extra == 'dev'
Requires-Dist: types-redis ; extra == 'dev'
Requires-Dist: types-termcolor ; extra == 'dev'
Requires-Dist: twine ; extra == 'dev'
Requires-Dist: types-tabulate ; extra == 'dev'
Requires-Dist: wheel ; extra == 'dev'
Provides-Extra: faiss
Requires-Dist: faiss-gpu ; extra == 'faiss'
Provides-Extra: nmslib
Requires-Dist: nmslib ; extra == 'nmslib'
Provides-Extra: redis
Requires-Dist: redis ; extra == 'redis'
Provides-Extra: tensorflow
Requires-Dist: tensorflow <=2.11,>=2.7 ; extra == 'tensorflow'
Provides-Extra: tensorflow-cpu
Requires-Dist: tensorflow-cpu <=2.11,>=2.7 ; extra == 'tensorflow-cpu'
Provides-Extra: tensorflow-gpu
Requires-Dist: tensorflow-gpu <=2.11,>=2.7 ; extra == 'tensorflow-gpu'
Provides-Extra: visualization
Requires-Dist: bokeh ; extra == 'visualization'
Requires-Dist: umap-learn ; extra == 'visualization'
Requires-Dist: matplotlib ; extra == 'visualization'
Requires-Dist: Pillow ; extra == 'visualization'
Requires-Dist: distinctipy ; extra == 'visualization'
